{
 "ticker": "PLTR",
 "cik": "0001321655",
 "entityName": "Palantir Technologies Inc.",
 "retrievedAt": "2026-07-24T06:03:49.676499Z",
 "fields": {
  "buyback": [
   {
    "value": 7706000,
    "unit": "USD",
    "periodStart": "2018-01-01",
    "periodEnd": "2018-12-31",
    "fiscalYear": 2020,
    "fiscalPeriod": "FY",
    "form": "10-K",
    "filedDate": "2021-02-26",
    "accessionNumber": "0001193125-21-060650",
    "xbrlTag": "us-gaap:PaymentsForRepurchaseOfCommonStock",
    "sourceType": "SEC",
    "sourceStatus": "reported",
    "restated": false,
    "supersedes": null,
    "confidence": 100
   },
   {
    "value": 11202000,
    "unit": "USD",
    "periodStart": "2019-01-01",
    "periodEnd": "2019-12-31",
    "fiscalYear": 2021,
    "fiscalPeriod": "FY",
    "form": "10-K",
    "filedDate": "2022-02-24",
    "accessionNumber": "0001193125-22-050913",
    "xbrlTag": "us-gaap:PaymentsForRepurchaseOfCommonStock",
    "sourceType": "SEC",
    "sourceStatus": "reported",
    "restated": true,
    "supersedes": {
     "value": 11202000,
     "filed": "2021-02-26",
     "accn": "0001193125-21-060650"
    },
    "confidence": 100
   },
   {
    "value": 3777000,
    "unit": "USD",
    "periodStart": "2020-01-01",
    "periodEnd": "2020-12-31",
    "fiscalYear": 2021,
    "fiscalPeriod": "FY",
    "form": "10-K",
    "filedDate": "2022-02-24",
    "accessionNumber": "0001193125-22-050913",
    "xbrlTag": "us-gaap:PaymentsForRepurchaseOfCommonStock",
    "sourceType": "SEC",
    "sourceStatus": "reported",
    "restated": true,
    "supersedes": {
     "value": 3777000,
     "filed": "2021-02-26",
     "accn": "0001193125-21-060650"
    },
    "confidence": 100
   },
   {
    "value": 0,
    "unit": "USD",
    "periodStart": "2021-01-01",
    "periodEnd": "2021-12-31",
    "fiscalYear": 2021,
    "fiscalPeriod": "FY",
    "form": "10-K",
    "filedDate": "2022-02-24",
    "accessionNumber": "0001193125-22-050913",
    "xbrlTag": "us-gaap:PaymentsForRepurchaseOfCommonStock",
    "sourceType": "SEC",
    "sourceStatus": "reported",
    "restated": false,
    "supersedes": null,
    "confidence": 100
   },
   {
    "value": 0,
    "unit": "USD",
    "periodStart": "2022-01-01",
    "periodEnd": "2022-12-31",
    "fiscalYear": 2024,
    "fiscalPeriod": "FY",
    "form": "10-K",
    "filedDate": "2025-02-18",
    "accessionNumber": "0001321655-25-000022",
    "xbrlTag": "us-gaap:PaymentsForRepurchaseOfCommonStock",
    "sourceType": "SEC",
    "sourceStatus": "reported",
    "restated": false,
    "supersedes": null,
    "confidence": 100
   },
   {
    "value": 0,
    "unit": "USD",
    "periodStart": "2023-01-01",
    "periodEnd": "2023-12-31",
    "fiscalYear": 2025,
    "fiscalPeriod": "FY",
    "form": "10-K",
    "filedDate": "2026-02-17",
    "accessionNumber": "0001321655-26-000011",
    "xbrlTag": "us-gaap:PaymentsForRepurchaseOfCommonStock",
    "sourceType": "SEC",
    "sourceStatus": "reported",
    "restated": true,
    "supersedes": {
     "value": 0,
     "filed": "2025-02-18",
     "accn": "0001321655-25-000022"
    },
    "confidence": 100
   },
   {
    "value": 64196000,
    "unit": "USD",
    "periodStart": "2024-01-01",
    "periodEnd": "2024-12-31",
    "fiscalYear": 2025,
    "fiscalPeriod": "FY",
    "form": "10-K",
    "filedDate": "2026-02-17",
    "accessionNumber": "0001321655-26-000011",
    "xbrlTag": "us-gaap:PaymentsForRepurchaseOfCommonStock",
    "sourceType": "SEC",
    "sourceStatus": "reported",
    "restated": true,
    "supersedes": {
     "value": 64196000,
     "filed": "2025-02-18",
     "accn": "0001321655-25-000022"
    },
    "confidence": 100
   },
   {
    "value": 74985000,
    "unit": "USD",
    "periodStart": "2025-01-01",
    "periodEnd": "2025-12-31",
    "fiscalYear": 2025,
    "fiscalPeriod": "FY",
    "form": "10-K",
    "filedDate": "2026-02-17",
    "accessionNumber": "0001321655-26-000011",
    "xbrlTag": "us-gaap:PaymentsForRepurchaseOfCommonStock",
    "sourceType": "SEC",
    "sourceStatus": "reported",
    "restated": false,
    "supersedes": null,
    "confidence": 100
   }
  ],
  "capex": [
   {
    "value": 13004000,
    "unit": "USD",
    "periodStart": "2018-01-01",
    "periodEnd": "2018-12-31",
    "fiscalYear": 2020,
    "fiscalPeriod": "FY",
    "form": "10-K",
    "filedDate": "2021-02-26",
    "accessionNumber": "0001193125-21-060650",
    "xbrlTag": "us-gaap:PaymentsToAcquirePropertyPlantAndEquipment",
    "sourceType": "SEC",
    "sourceStatus": "reported",
    "restated": false,
    "supersedes": null,
    "confidence": 100
   },
   {
    "value": 13096000,
    "unit": "USD",
    "periodStart": "2019-01-01",
    "periodEnd": "2019-12-31",
    "fiscalYear": 2021,
    "fiscalPeriod": "FY",
    "form": "10-K",
    "filedDate": "2022-02-24",
    "accessionNumber": "0001193125-22-050913",
    "xbrlTag": "us-gaap:PaymentsToAcquirePropertyPlantAndEquipment",
    "sourceType": "SEC",
    "sourceStatus": "reported",
    "restated": true,
    "supersedes": {
     "value": 13096000,
     "filed": "2021-02-26",
     "accn": "0001193125-21-060650"
    },
    "confidence": 100
   },
   {
    "value": 12236000,
    "unit": "USD",
    "periodStart": "2020-01-01",
    "periodEnd": "2020-12-31",
    "fiscalYear": 2022,
    "fiscalPeriod": "FY",
    "form": "10-K",
    "filedDate": "2023-02-21",
    "accessionNumber": "0001321655-23-000011",
    "xbrlTag": "us-gaap:PaymentsToAcquirePropertyPlantAndEquipment",
    "sourceType": "SEC",
    "sourceStatus": "reported",
    "restated": true,
    "supersedes": {
     "value": 12236000,
     "filed": "2022-02-24",
     "accn": "0001193125-22-050913"
    },
    "confidence": 100
   },
   {
    "value": 12627000,
    "unit": "USD",
    "periodStart": "2021-01-01",
    "periodEnd": "2021-12-31",
    "fiscalYear": 2023,
    "fiscalPeriod": "FY",
    "form": "10-K",
    "filedDate": "2024-02-20",
    "accessionNumber": "0001321655-24-000022",
    "xbrlTag": "us-gaap:PaymentsToAcquirePropertyPlantAndEquipment",
    "sourceType": "SEC",
    "sourceStatus": "reported",
    "restated": true,
    "supersedes": {
     "value": 12627000,
     "filed": "2023-02-21",
     "accn": "0001321655-23-000011"
    },
    "confidence": 100
   },
   {
    "value": 40027000,
    "unit": "USD",
    "periodStart": "2022-01-01",
    "periodEnd": "2022-12-31",
    "fiscalYear": 2024,
    "fiscalPeriod": "FY",
    "form": "10-K",
    "filedDate": "2025-02-18",
    "accessionNumber": "0001321655-25-000022",
    "xbrlTag": "us-gaap:PaymentsToAcquirePropertyPlantAndEquipment",
    "sourceType": "SEC",
    "sourceStatus": "reported",
    "restated": true,
    "supersedes": {
     "value": 40027000,
     "filed": "2024-02-20",
     "accn": "0001321655-24-000022"
    },
    "confidence": 100
   },
   {
    "value": 15114000,
    "unit": "USD",
    "periodStart": "2023-01-01",
    "periodEnd": "2023-12-31",
    "fiscalYear": 2025,
    "fiscalPeriod": "FY",
    "form": "10-K",
    "filedDate": "2026-02-17",
    "accessionNumber": "0001321655-26-000011",
    "xbrlTag": "us-gaap:PaymentsToAcquirePropertyPlantAndEquipment",
    "sourceType": "SEC",
    "sourceStatus": "reported",
    "restated": true,
    "supersedes": {
     "value": 15114000,
     "filed": "2025-02-18",
     "accn": "0001321655-25-000022"
    },
    "confidence": 100
   },
   {
    "value": 12634000,
    "unit": "USD",
    "periodStart": "2024-01-01",
    "periodEnd": "2024-12-31",
    "fiscalYear": 2025,
    "fiscalPeriod": "FY",
    "form": "10-K",
    "filedDate": "2026-02-17",
    "accessionNumber": "0001321655-26-000011",
    "xbrlTag": "us-gaap:PaymentsToAcquirePropertyPlantAndEquipment",
    "sourceType": "SEC",
    "sourceStatus": "reported",
    "restated": true,
    "supersedes": {
     "value": 12634000,
     "filed": "2025-02-18",
     "accn": "0001321655-25-000022"
    },
    "confidence": 100
   },
   {
    "value": 33882000,
    "unit": "USD",
    "periodStart": "2025-01-01",
    "periodEnd": "2025-12-31",
    "fiscalYear": 2025,
    "fiscalPeriod": "FY",
    "form": "10-K",
    "filedDate": "2026-02-17",
    "accessionNumber": "0001321655-26-000011",
    "xbrlTag": "us-gaap:PaymentsToAcquirePropertyPlantAndEquipment",
    "sourceType": "SEC",
    "sourceStatus": "reported",
    "restated": false,
    "supersedes": null,
    "confidence": 100
   }
  ],
  "dilShares": [
   {
    "value": 544014393,
    "unit": "shares",
    "periodStart": "2018-01-01",
    "periodEnd": "2018-12-31",
    "fiscalYear": 2020,
    "fiscalPeriod": "FY",
    "form": "10-K",
    "filedDate": "2021-02-26",
    "accessionNumber": "0001193125-21-060650",
    "xbrlTag": "us-gaap:WeightedAverageNumberOfDilutedSharesOutstanding",
    "sourceType": "SEC",
    "sourceStatus": "reported",
    "restated": false,
    "supersedes": null,
    "confidence": 100
   },
   {
    "value": 576959000,
    "unit": "shares",
    "periodStart": "2019-01-01",
    "periodEnd": "2019-12-31",
    "fiscalYear": 2021,
    "fiscalPeriod": "FY",
    "form": "10-K",
    "filedDate": "2022-02-24",
    "accessionNumber": "0001193125-22-050913",
    "xbrlTag": "us-gaap:WeightedAverageNumberOfDilutedSharesOutstanding",
    "sourceType": "SEC",
    "sourceStatus": "reported",
    "restated": true,
    "supersedes": {
     "value": 576958560,
     "filed": "2021-02-26",
     "accn": "0001193125-21-060650"
    },
    "confidence": 100
   },
   {
    "value": 979330000,
    "unit": "shares",
    "periodStart": "2020-01-01",
    "periodEnd": "2020-12-31",
    "fiscalYear": 2022,
    "fiscalPeriod": "FY",
    "form": "10-K",
    "filedDate": "2023-02-21",
    "accessionNumber": "0001321655-23-000011",
    "xbrlTag": "us-gaap:WeightedAverageNumberOfDilutedSharesOutstanding",
    "sourceType": "SEC",
    "sourceStatus": "reported",
    "restated": true,
    "supersedes": {
     "value": 979330000,
     "filed": "2022-02-24",
     "accn": "0001193125-22-050913"
    },
    "confidence": 100
   },
   {
    "value": 1923617000,
    "unit": "shares",
    "periodStart": "2021-01-01",
    "periodEnd": "2021-12-31",
    "fiscalYear": 2023,
    "fiscalPeriod": "FY",
    "form": "10-K",
    "filedDate": "2024-02-20",
    "accessionNumber": "0001321655-24-000022",
    "xbrlTag": "us-gaap:WeightedAverageNumberOfDilutedSharesOutstanding",
    "sourceType": "SEC",
    "sourceStatus": "reported",
    "restated": true,
    "supersedes": {
     "value": 1923617000,
     "filed": "2023-02-21",
     "accn": "0001321655-23-000011"
    },
    "confidence": 100
   },
   {
    "value": 2063793000,
    "unit": "shares",
    "periodStart": "2022-01-01",
    "periodEnd": "2022-12-31",
    "fiscalYear": 2024,
    "fiscalPeriod": "FY",
    "form": "10-K",
    "filedDate": "2025-02-18",
    "accessionNumber": "0001321655-25-000022",
    "xbrlTag": "us-gaap:WeightedAverageNumberOfDilutedSharesOutstanding",
    "sourceType": "SEC",
    "sourceStatus": "reported",
    "restated": true,
    "supersedes": {
     "value": 2063793000,
     "filed": "2024-02-20",
     "accn": "0001321655-24-000022"
    },
    "confidence": 100
   },
   {
    "value": 2297927000,
    "unit": "shares",
    "periodStart": "2023-01-01",
    "periodEnd": "2023-12-31",
    "fiscalYear": 2025,
    "fiscalPeriod": "FY",
    "form": "10-K",
    "filedDate": "2026-02-17",
    "accessionNumber": "0001321655-26-000011",
    "xbrlTag": "us-gaap:WeightedAverageNumberOfDilutedSharesOutstanding",
    "sourceType": "SEC",
    "sourceStatus": "reported",
    "restated": true,
    "supersedes": {
     "value": 2297927000,
     "filed": "2025-02-18",
     "accn": "0001321655-25-000022"
    },
    "confidence": 100
   },
   {
    "value": 2450818000,
    "unit": "shares",
    "periodStart": "2024-01-01",
    "periodEnd": "2024-12-31",
    "fiscalYear": 2025,
    "fiscalPeriod": "FY",
    "form": "10-K",
    "filedDate": "2026-02-17",
    "accessionNumber": "0001321655-26-000011",
    "xbrlTag": "us-gaap:WeightedAverageNumberOfDilutedSharesOutstanding",
    "sourceType": "SEC",
    "sourceStatus": "reported",
    "restated": true,
    "supersedes": {
     "value": 2450818000,
     "filed": "2025-02-18",
     "accn": "0001321655-25-000022"
    },
    "confidence": 100
   },
   {
    "value": 2565197000,
    "unit": "shares",
    "periodStart": "2025-01-01",
    "periodEnd": "2025-12-31",
    "fiscalYear": 2025,
    "fiscalPeriod": "FY",
    "form": "10-K",
    "filedDate": "2026-02-17",
    "accessionNumber": "0001321655-26-000011",
    "xbrlTag": "us-gaap:WeightedAverageNumberOfDilutedSharesOutstanding",
    "sourceType": "SEC",
    "sourceStatus": "reported",
    "restated": false,
    "supersedes": null,
    "confidence": 100
   }
  ],
  "esppProceeds": [
   {
    "value": 96480000,
    "unit": "USD",
    "periodStart": "2018-01-01",
    "periodEnd": "2018-12-31",
    "fiscalYear": 2020,
    "fiscalPeriod": "FY",
    "form": "10-K",
    "filedDate": "2021-02-26",
    "accessionNumber": "0001193125-21-060650",
    "xbrlTag": "us-gaap:ProceedsFromIssuanceOfCommonStock",
    "sourceType": "SEC",
    "sourceStatus": "reported",
    "restated": false,
    "supersedes": null,
    "confidence": 100
   },
   {
    "value": 544413000,
    "unit": "USD",
    "periodStart": "2019-01-01",
    "periodEnd": "2019-12-31",
    "fiscalYear": 2021,
    "fiscalPeriod": "FY",
    "form": "10-K",
    "filedDate": "2022-02-24",
    "accessionNumber": "0001193125-22-050913",
    "xbrlTag": "us-gaap:ProceedsFromIssuanceOfCommonStock",
    "sourceType": "SEC",
    "sourceStatus": "reported",
    "restated": true,
    "supersedes": {
     "value": 100000000,
     "filed": "2021-02-26",
     "accn": "0001193125-21-060650"
    },
    "confidence": 100
   },
   {
    "value": 199369000,
    "unit": "USD",
    "periodStart": "2020-01-01",
    "periodEnd": "2020-12-31",
    "fiscalYear": 2022,
    "fiscalPeriod": "FY",
    "form": "10-K",
    "filedDate": "2023-02-21",
    "accessionNumber": "0001321655-23-000011",
    "xbrlTag": "us-gaap:ProceedsFromIssuanceOfCommonStock",
    "sourceType": "SEC",
    "sourceStatus": "reported",
    "restated": true,
    "supersedes": {
     "value": 199369000,
     "filed": "2022-02-24",
     "accn": "0001193125-22-050913"
    },
    "confidence": 100
   },
   {
    "value": 0,
    "unit": "USD",
    "periodStart": "2021-01-01",
    "periodEnd": "2021-12-31",
    "fiscalYear": 2022,
    "fiscalPeriod": "FY",
    "form": "10-K",
    "filedDate": "2023-02-21",
    "accessionNumber": "0001321655-23-000011",
    "xbrlTag": "us-gaap:ProceedsFromIssuanceOfCommonStock",
    "sourceType": "SEC",
    "sourceStatus": "reported",
    "restated": true,
    "supersedes": {
     "value": 0,
     "filed": "2022-02-24",
     "accn": "0001193125-22-050913"
    },
    "confidence": 100
   },
   {
    "value": 0,
    "unit": "USD",
    "periodStart": "2022-01-01",
    "periodEnd": "2022-12-31",
    "fiscalYear": 2022,
    "fiscalPeriod": "FY",
    "form": "10-K",
    "filedDate": "2023-02-21",
    "accessionNumber": "0001321655-23-000011",
    "xbrlTag": "us-gaap:ProceedsFromIssuanceOfCommonStock",
    "sourceType": "SEC",
    "sourceStatus": "reported",
    "restated": false,
    "supersedes": null,
    "confidence": 100
   }
  ],
  "netIncome": [
   {
    "value": -580027000,
    "unit": "USD",
    "periodStart": "2018-01-01",
    "periodEnd": "2018-12-31",
    "fiscalYear": 2020,
    "fiscalPeriod": "FY",
    "form": "10-K",
    "filedDate": "2021-02-26",
    "accessionNumber": "0001193125-21-060650",
    "xbrlTag": "us-gaap:NetIncomeLoss",
    "sourceType": "SEC",
    "sourceStatus": "reported",
    "restated": false,
    "supersedes": null,
    "confidence": 100
   },
   {
    "value": -579646000,
    "unit": "USD",
    "periodStart": "2019-01-01",
    "periodEnd": "2019-12-31",
    "fiscalYear": 2021,
    "fiscalPeriod": "FY",
    "form": "10-K",
    "filedDate": "2022-02-24",
    "accessionNumber": "0001193125-22-050913",
    "xbrlTag": "us-gaap:NetIncomeLoss",
    "sourceType": "SEC",
    "sourceStatus": "reported",
    "restated": true,
    "supersedes": {
     "value": -579646000,
     "filed": "2021-02-26",
     "accn": "0001193125-21-060650"
    },
    "confidence": 100
   },
   {
    "value": -1166391000,
    "unit": "USD",
    "periodStart": "2020-01-01",
    "periodEnd": "2020-12-31",
    "fiscalYear": 2022,
    "fiscalPeriod": "FY",
    "form": "10-K",
    "filedDate": "2023-02-21",
    "accessionNumber": "0001321655-23-000011",
    "xbrlTag": "us-gaap:NetIncomeLoss",
    "sourceType": "SEC",
    "sourceStatus": "reported",
    "restated": true,
    "supersedes": {
     "value": -1166391000,
     "filed": "2022-02-24",
     "accn": "0001193125-22-050913"
    },
    "confidence": 100
   },
   {
    "value": -520379000,
    "unit": "USD",
    "periodStart": "2021-01-01",
    "periodEnd": "2021-12-31",
    "fiscalYear": 2023,
    "fiscalPeriod": "FY",
    "form": "10-K",
    "filedDate": "2024-02-20",
    "accessionNumber": "0001321655-24-000022",
    "xbrlTag": "us-gaap:NetIncomeLoss",
    "sourceType": "SEC",
    "sourceStatus": "reported",
    "restated": true,
    "supersedes": {
     "value": -520379000,
     "filed": "2023-02-21",
     "accn": "0001321655-23-000011"
    },
    "confidence": 100
   },
   {
    "value": -373705000,
    "unit": "USD",
    "periodStart": "2022-01-01",
    "periodEnd": "2022-12-31",
    "fiscalYear": 2024,
    "fiscalPeriod": "FY",
    "form": "10-K",
    "filedDate": "2025-02-18",
    "accessionNumber": "0001321655-25-000022",
    "xbrlTag": "us-gaap:NetIncomeLoss",
    "sourceType": "SEC",
    "sourceStatus": "reported",
    "restated": true,
    "supersedes": {
     "value": -373705000,
     "filed": "2024-02-20",
     "accn": "0001321655-24-000022"
    },
    "confidence": 100
   },
   {
    "value": 209825000,
    "unit": "USD",
    "periodStart": "2023-01-01",
    "periodEnd": "2023-12-31",
    "fiscalYear": 2025,
    "fiscalPeriod": "FY",
    "form": "10-K",
    "filedDate": "2026-02-17",
    "accessionNumber": "0001321655-26-000011",
    "xbrlTag": "us-gaap:NetIncomeLoss",
    "sourceType": "SEC",
    "sourceStatus": "reported",
    "restated": true,
    "supersedes": {
     "value": 209825000,
     "filed": "2025-02-18",
     "accn": "0001321655-25-000022"
    },
    "confidence": 100
   },
   {
    "value": 462190000,
    "unit": "USD",
    "periodStart": "2024-01-01",
    "periodEnd": "2024-12-31",
    "fiscalYear": 2025,
    "fiscalPeriod": "FY",
    "form": "10-K",
    "filedDate": "2026-02-17",
    "accessionNumber": "0001321655-26-000011",
    "xbrlTag": "us-gaap:NetIncomeLoss",
    "sourceType": "SEC",
    "sourceStatus": "reported",
    "restated": true,
    "supersedes": {
     "value": 462190000,
     "filed": "2025-02-18",
     "accn": "0001321655-25-000022"
    },
    "confidence": 100
   },
   {
    "value": 1625033000,
    "unit": "USD",
    "periodStart": "2025-01-01",
    "periodEnd": "2025-12-31",
    "fiscalYear": 2025,
    "fiscalPeriod": "FY",
    "form": "10-K",
    "filedDate": "2026-02-17",
    "accessionNumber": "0001321655-26-000011",
    "xbrlTag": "us-gaap:NetIncomeLoss",
    "sourceType": "SEC",
    "sourceStatus": "reported",
    "restated": false,
    "supersedes": null,
    "confidence": 100
   }
  ],
  "ocf": [
   {
    "value": -39012000,
    "unit": "USD",
    "periodStart": "2018-01-01",
    "periodEnd": "2018-12-31",
    "fiscalYear": 2020,
    "fiscalPeriod": "FY",
    "form": "10-K",
    "filedDate": "2021-02-26",
    "accessionNumber": "0001193125-21-060650",
    "xbrlTag": "us-gaap:NetCashProvidedByUsedInOperatingActivities",
    "sourceType": "SEC",
    "sourceStatus": "reported",
    "restated": false,
    "supersedes": null,
    "confidence": 100
   },
   {
    "value": -165215000,
    "unit": "USD",
    "periodStart": "2019-01-01",
    "periodEnd": "2019-12-31",
    "fiscalYear": 2021,
    "fiscalPeriod": "FY",
    "form": "10-K",
    "filedDate": "2022-02-24",
    "accessionNumber": "0001193125-22-050913",
    "xbrlTag": "us-gaap:NetCashProvidedByUsedInOperatingActivities",
    "sourceType": "SEC",
    "sourceStatus": "reported",
    "restated": true,
    "supersedes": {
     "value": -165215000,
     "filed": "2021-02-26",
     "accn": "0001193125-21-060650"
    },
    "confidence": 100
   },
   {
    "value": -296608000,
    "unit": "USD",
    "periodStart": "2020-01-01",
    "periodEnd": "2020-12-31",
    "fiscalYear": 2022,
    "fiscalPeriod": "FY",
    "form": "10-K",
    "filedDate": "2023-02-21",
    "accessionNumber": "0001321655-23-000011",
    "xbrlTag": "us-gaap:NetCashProvidedByUsedInOperatingActivities",
    "sourceType": "SEC",
    "sourceStatus": "reported",
    "restated": true,
    "supersedes": {
     "value": -296608000,
     "filed": "2022-02-24",
     "accn": "0001193125-22-050913"
    },
    "confidence": 100
   },
   {
    "value": 333851000,
    "unit": "USD",
    "periodStart": "2021-01-01",
    "periodEnd": "2021-12-31",
    "fiscalYear": 2023,
    "fiscalPeriod": "FY",
    "form": "10-K",
    "filedDate": "2024-02-20",
    "accessionNumber": "0001321655-24-000022",
    "xbrlTag": "us-gaap:NetCashProvidedByUsedInOperatingActivities",
    "sourceType": "SEC",
    "sourceStatus": "reported",
    "restated": true,
    "supersedes": {
     "value": 333851000,
     "filed": "2023-02-21",
     "accn": "0001321655-23-000011"
    },
    "confidence": 100
   },
   {
    "value": 223737000,
    "unit": "USD",
    "periodStart": "2022-01-01",
    "periodEnd": "2022-12-31",
    "fiscalYear": 2024,
    "fiscalPeriod": "FY",
    "form": "10-K",
    "filedDate": "2025-02-18",
    "accessionNumber": "0001321655-25-000022",
    "xbrlTag": "us-gaap:NetCashProvidedByUsedInOperatingActivities",
    "sourceType": "SEC",
    "sourceStatus": "reported",
    "restated": true,
    "supersedes": {
     "value": 223737000,
     "filed": "2024-02-20",
     "accn": "0001321655-24-000022"
    },
    "confidence": 100
   },
   {
    "value": 712183000,
    "unit": "USD",
    "periodStart": "2023-01-01",
    "periodEnd": "2023-12-31",
    "fiscalYear": 2025,
    "fiscalPeriod": "FY",
    "form": "10-K",
    "filedDate": "2026-02-17",
    "accessionNumber": "0001321655-26-000011",
    "xbrlTag": "us-gaap:NetCashProvidedByUsedInOperatingActivities",
    "sourceType": "SEC",
    "sourceStatus": "reported",
    "restated": true,
    "supersedes": {
     "value": 712183000,
     "filed": "2025-02-18",
     "accn": "0001321655-25-000022"
    },
    "confidence": 100
   },
   {
    "value": 1153865000,
    "unit": "USD",
    "periodStart": "2024-01-01",
    "periodEnd": "2024-12-31",
    "fiscalYear": 2025,
    "fiscalPeriod": "FY",
    "form": "10-K",
    "filedDate": "2026-02-17",
    "accessionNumber": "0001321655-26-000011",
    "xbrlTag": "us-gaap:NetCashProvidedByUsedInOperatingActivities",
    "sourceType": "SEC",
    "sourceStatus": "reported",
    "restated": true,
    "supersedes": {
     "value": 1153865000,
     "filed": "2025-02-18",
     "accn": "0001321655-25-000022"
    },
    "confidence": 100
   },
   {
    "value": 2134473000,
    "unit": "USD",
    "periodStart": "2025-01-01",
    "periodEnd": "2025-12-31",
    "fiscalYear": 2025,
    "fiscalPeriod": "FY",
    "form": "10-K",
    "filedDate": "2026-02-17",
    "accessionNumber": "0001321655-26-000011",
    "xbrlTag": "us-gaap:NetCashProvidedByUsedInOperatingActivities",
    "sourceType": "SEC",
    "sourceStatus": "reported",
    "restated": false,
    "supersedes": null,
    "confidence": 100
   }
  ],
  "revenue": [
   {
    "value": 595409000,
    "unit": "USD",
    "periodStart": "2018-01-01",
    "periodEnd": "2018-12-31",
    "fiscalYear": 2020,
    "fiscalPeriod": "FY",
    "form": "10-K",
    "filedDate": "2021-02-26",
    "accessionNumber": "0001193125-21-060650",
    "xbrlTag": "us-gaap:RevenueFromContractWithCustomerExcludingAssessedTax",
    "sourceType": "SEC",
    "sourceStatus": "reported",
    "restated": false,
    "supersedes": null,
    "confidence": 100
   },
   {
    "value": 742555000,
    "unit": "USD",
    "periodStart": "2019-01-01",
    "periodEnd": "2019-12-31",
    "fiscalYear": 2021,
    "fiscalPeriod": "FY",
    "form": "10-K",
    "filedDate": "2022-02-24",
    "accessionNumber": "0001193125-22-050913",
    "xbrlTag": "us-gaap:RevenueFromContractWithCustomerExcludingAssessedTax",
    "sourceType": "SEC",
    "sourceStatus": "reported",
    "restated": true,
    "supersedes": {
     "value": 742555000,
     "filed": "2021-02-26",
     "accn": "0001193125-21-060650"
    },
    "confidence": 100
   },
   {
    "value": 1092673000,
    "unit": "USD",
    "periodStart": "2020-01-01",
    "periodEnd": "2020-12-31",
    "fiscalYear": 2022,
    "fiscalPeriod": "FY",
    "form": "10-K",
    "filedDate": "2023-02-21",
    "accessionNumber": "0001321655-23-000011",
    "xbrlTag": "us-gaap:RevenueFromContractWithCustomerExcludingAssessedTax",
    "sourceType": "SEC",
    "sourceStatus": "reported",
    "restated": true,
    "supersedes": {
     "value": 1092673000,
     "filed": "2022-02-24",
     "accn": "0001193125-22-050913"
    },
    "confidence": 100
   },
   {
    "value": 1541889000,
    "unit": "USD",
    "periodStart": "2021-01-01",
    "periodEnd": "2021-12-31",
    "fiscalYear": 2023,
    "fiscalPeriod": "FY",
    "form": "10-K",
    "filedDate": "2024-02-20",
    "accessionNumber": "0001321655-24-000022",
    "xbrlTag": "us-gaap:RevenueFromContractWithCustomerExcludingAssessedTax",
    "sourceType": "SEC",
    "sourceStatus": "reported",
    "restated": true,
    "supersedes": {
     "value": 1541889000,
     "filed": "2023-02-21",
     "accn": "0001321655-23-000011"
    },
    "confidence": 100
   },
   {
    "value": 1905871000,
    "unit": "USD",
    "periodStart": "2022-01-01",
    "periodEnd": "2022-12-31",
    "fiscalYear": 2024,
    "fiscalPeriod": "FY",
    "form": "10-K",
    "filedDate": "2025-02-18",
    "accessionNumber": "0001321655-25-000022",
    "xbrlTag": "us-gaap:RevenueFromContractWithCustomerExcludingAssessedTax",
    "sourceType": "SEC",
    "sourceStatus": "reported",
    "restated": true,
    "supersedes": {
     "value": 1905871000,
     "filed": "2024-02-20",
     "accn": "0001321655-24-000022"
    },
    "confidence": 100
   },
   {
    "value": 2225012000,
    "unit": "USD",
    "periodStart": "2023-01-01",
    "periodEnd": "2023-12-31",
    "fiscalYear": 2025,
    "fiscalPeriod": "FY",
    "form": "10-K",
    "filedDate": "2026-02-17",
    "accessionNumber": "0001321655-26-000011",
    "xbrlTag": "us-gaap:RevenueFromContractWithCustomerExcludingAssessedTax",
    "sourceType": "SEC",
    "sourceStatus": "reported",
    "restated": true,
    "supersedes": {
     "value": 2225012000,
     "filed": "2025-02-18",
     "accn": "0001321655-25-000022"
    },
    "confidence": 100
   },
   {
    "value": 2865507000,
    "unit": "USD",
    "periodStart": "2024-01-01",
    "periodEnd": "2024-12-31",
    "fiscalYear": 2025,
    "fiscalPeriod": "FY",
    "form": "10-K",
    "filedDate": "2026-02-17",
    "accessionNumber": "0001321655-26-000011",
    "xbrlTag": "us-gaap:RevenueFromContractWithCustomerExcludingAssessedTax",
    "sourceType": "SEC",
    "sourceStatus": "reported",
    "restated": true,
    "supersedes": {
     "value": 2865507000,
     "filed": "2025-02-18",
     "accn": "0001321655-25-000022"
    },
    "confidence": 100
   },
   {
    "value": 4475446000,
    "unit": "USD",
    "periodStart": "2025-01-01",
    "periodEnd": "2025-12-31",
    "fiscalYear": 2025,
    "fiscalPeriod": "FY",
    "form": "10-K",
    "filedDate": "2026-02-17",
    "accessionNumber": "0001321655-26-000011",
    "xbrlTag": "us-gaap:RevenueFromContractWithCustomerExcludingAssessedTax",
    "sourceType": "SEC",
    "sourceStatus": "reported",
    "restated": false,
    "supersedes": null,
    "confidence": 100
   }
  ],
  "sbc": [
   {
    "value": 248503000,
    "unit": "USD",
    "periodStart": "2018-01-01",
    "periodEnd": "2018-12-31",
    "fiscalYear": 2020,
    "fiscalPeriod": "FY",
    "form": "10-K",
    "filedDate": "2021-02-26",
    "accessionNumber": "0001193125-21-060650",
    "xbrlTag": "us-gaap:ShareBasedCompensation",
    "sourceType": "SEC",
    "sourceStatus": "reported",
    "restated": false,
    "supersedes": null,
    "confidence": 100
   },
   {
    "value": 241970000,
    "unit": "USD",
    "periodStart": "2019-01-01",
    "periodEnd": "2019-12-31",
    "fiscalYear": 2021,
    "fiscalPeriod": "FY",
    "form": "10-K",
    "filedDate": "2022-02-24",
    "accessionNumber": "0001193125-22-050913",
    "xbrlTag": "us-gaap:ShareBasedCompensation",
    "sourceType": "SEC",
    "sourceStatus": "reported",
    "restated": true,
    "supersedes": {
     "value": 241970000,
     "filed": "2021-02-26",
     "accn": "0001193125-21-060650"
    },
    "confidence": 100
   },
   {
    "value": 1270702000,
    "unit": "USD",
    "periodStart": "2020-01-01",
    "periodEnd": "2020-12-31",
    "fiscalYear": 2022,
    "fiscalPeriod": "FY",
    "form": "10-K",
    "filedDate": "2023-02-21",
    "accessionNumber": "0001321655-23-000011",
    "xbrlTag": "us-gaap:ShareBasedCompensation",
    "sourceType": "SEC",
    "sourceStatus": "reported",
    "restated": true,
    "supersedes": {
     "value": 1270702000,
     "filed": "2022-02-24",
     "accn": "0001193125-22-050913"
    },
    "confidence": 100
   },
   {
    "value": 778215000,
    "unit": "USD",
    "periodStart": "2021-01-01",
    "periodEnd": "2021-12-31",
    "fiscalYear": 2023,
    "fiscalPeriod": "FY",
    "form": "10-K",
    "filedDate": "2024-02-20",
    "accessionNumber": "0001321655-24-000022",
    "xbrlTag": "us-gaap:ShareBasedCompensation",
    "sourceType": "SEC",
    "sourceStatus": "reported",
    "restated": true,
    "supersedes": {
     "value": 778215000,
     "filed": "2023-02-21",
     "accn": "0001321655-23-000011"
    },
    "confidence": 100
   },
   {
    "value": 564798000,
    "unit": "USD",
    "periodStart": "2022-01-01",
    "periodEnd": "2022-12-31",
    "fiscalYear": 2024,
    "fiscalPeriod": "FY",
    "form": "10-K",
    "filedDate": "2025-02-18",
    "accessionNumber": "0001321655-25-000022",
    "xbrlTag": "us-gaap:ShareBasedCompensation",
    "sourceType": "SEC",
    "sourceStatus": "reported",
    "restated": true,
    "supersedes": {
     "value": 564798000,
     "filed": "2024-02-20",
     "accn": "0001321655-24-000022"
    },
    "confidence": 100
   },
   {
    "value": 475903000,
    "unit": "USD",
    "periodStart": "2023-01-01",
    "periodEnd": "2023-12-31",
    "fiscalYear": 2025,
    "fiscalPeriod": "FY",
    "form": "10-K",
    "filedDate": "2026-02-17",
    "accessionNumber": "0001321655-26-000011",
    "xbrlTag": "us-gaap:ShareBasedCompensation",
    "sourceType": "SEC",
    "sourceStatus": "reported",
    "restated": true,
    "supersedes": {
     "value": 475903000,
     "filed": "2025-02-18",
     "accn": "0001321655-25-000022"
    },
    "confidence": 100
   },
   {
    "value": 691638000,
    "unit": "USD",
    "periodStart": "2024-01-01",
    "periodEnd": "2024-12-31",
    "fiscalYear": 2025,
    "fiscalPeriod": "FY",
    "form": "10-K",
    "filedDate": "2026-02-17",
    "accessionNumber": "0001321655-26-000011",
    "xbrlTag": "us-gaap:ShareBasedCompensation",
    "sourceType": "SEC",
    "sourceStatus": "reported",
    "restated": true,
    "supersedes": {
     "value": 691638000,
     "filed": "2025-02-18",
     "accn": "0001321655-25-000022"
    },
    "confidence": 100
   },
   {
    "value": 684033000,
    "unit": "USD",
    "periodStart": "2025-01-01",
    "periodEnd": "2025-12-31",
    "fiscalYear": 2025,
    "fiscalPeriod": "FY",
    "form": "10-K",
    "filedDate": "2026-02-17",
    "accessionNumber": "0001321655-26-000011",
    "xbrlTag": "us-gaap:ShareBasedCompensation",
    "sourceType": "SEC",
    "sourceStatus": "reported",
    "restated": false,
    "supersedes": null,
    "confidence": 100
   }
  ],
  "taxWithholding": [
   {
    "value": 0,
    "unit": "USD",
    "periodStart": "2022-01-01",
    "periodEnd": "2022-12-31",
    "fiscalYear": 2024,
    "fiscalPeriod": "FY",
    "form": "10-K",
    "filedDate": "2025-02-18",
    "accessionNumber": "0001321655-25-000022",
    "xbrlTag": "us-gaap:PaymentsRelatedToTaxWithholdingForShareBasedCompensation",
    "sourceType": "SEC",
    "sourceStatus": "reported",
    "restated": false,
    "supersedes": null,
    "confidence": 100
   },
   {
    "value": 0,
    "unit": "USD",
    "periodStart": "2023-01-01",
    "periodEnd": "2023-12-31",
    "fiscalYear": 2025,
    "fiscalPeriod": "FY",
    "form": "10-K",
    "filedDate": "2026-02-17",
    "accessionNumber": "0001321655-26-000011",
    "xbrlTag": "us-gaap:PaymentsRelatedToTaxWithholdingForShareBasedCompensation",
    "sourceType": "SEC",
    "sourceStatus": "reported",
    "restated": true,
    "supersedes": {
     "value": 0,
     "filed": "2025-02-18",
     "accn": "0001321655-25-000022"
    },
    "confidence": 100
   },
   {
    "value": 218280000,
    "unit": "USD",
    "periodStart": "2024-01-01",
    "periodEnd": "2024-12-31",
    "fiscalYear": 2025,
    "fiscalPeriod": "FY",
    "form": "10-K",
    "filedDate": "2026-02-17",
    "accessionNumber": "0001321655-26-000011",
    "xbrlTag": "us-gaap:PaymentsRelatedToTaxWithholdingForShareBasedCompensation",
    "sourceType": "SEC",
    "sourceStatus": "reported",
    "restated": true,
    "supersedes": {
     "value": 218280000,
     "filed": "2025-02-18",
     "accn": "0001321655-25-000022"
    },
    "confidence": 100
   },
   {
    "value": 81117000,
    "unit": "USD",
    "periodStart": "2025-01-01",
    "periodEnd": "2025-12-31",
    "fiscalYear": 2025,
    "fiscalPeriod": "FY",
    "form": "10-K",
    "filedDate": "2026-02-17",
    "accessionNumber": "0001321655-26-000011",
    "xbrlTag": "us-gaap:PaymentsRelatedToTaxWithholdingForShareBasedCompensation",
    "sourceType": "SEC",
    "sourceStatus": "reported",
    "restated": false,
    "supersedes": null,
    "confidence": 100
   }
  ]
 },
 "latestFiling": {
  "filed": "2026-02-17",
  "form": "10-K",
  "accn": "0001321655-26-000011"
 }
}